[{"type": "Lec", "day": "MW", "start_time": "08:30", "end_time": "09:50", "spaces_available": "87", "number_registered": "87", "units": "4.0", "dclass_code": "R", "instructorName": ["Biblarz,Tim"]}, {"type": "Dis", "day": "M", "start_time": "12:00", "end_time": "12:50", "spaces_available": "25", "number_registered": "25", "units": "0.0", "dclass_code": "R", "instructorName": ""}, {"type": "Dis", "day": "M", "start_time": "13:00", "end_time": "13:50", "spaces_available": "25", "number_registered": "25", "units": "0.0", "dclass_code": "R", "instructorName": ""}, {"type": "Dis", "day": "F", "start_time": "12:00", "end_time": "12:50", "spaces_available": "25", "number_registered": "24", "units": "0.0", "dclass_code": "R", "instructorName": ["Shimada,Elisabeth"]}, {"type": "Dis", "day": "F", "start_time": "13:00", "end_time": "13:50", "spaces_available": "25", "number_registered": "13", "units": "0.0", "dclass_code": "R", "instructorName": ["Shimada,Elisabeth"]}]