[{"type": "Lec", "day": "TH", "start_time": "10:00", "end_time": "11:50", "spaces_available": "49", "number_registered": "49", "units": "4.0", "dclass_code": "R", "instructorName": ["Bassi,Vittorio"]}, {"type": "Dis", "day": "T", "start_time": "18:00", "end_time": "18:50", "spaces_available": "26", "number_registered": "26", "units": "0.0", "dclass_code": "R", "instructorName": ""}, {"type": "Dis", "day": "M", "start_time": "18:00", "end_time": "18:50", "spaces_available": "23", "number_registered": "23", "units": "0.0", "dclass_code": "R", "instructorName": ""}, {"type": "Lec", "day": "TH", "start_time": "16:00", "end_time": "17:50", "spaces_available": "51", "number_registered": "51", "units": "4.0", "dclass_code": "R", "instructorName": ["Weaver,Jeffrey"]}, {"type": "Dis", "day": "W", "start_time": "18:00", "end_time": "18:50", "spaces_available": "27", "number_registered": "27", "units": "0.0", "dclass_code": "R", "instructorName": ""}, {"type": "Dis", "day": "F", "start_time": "12:00", "end_time": "12:50", "spaces_available": "24", "number_registered": "24", "units": "0.0", "dclass_code": "R", "instructorName": ""}, {"type": "Lec", "day": "MW", "start_time": "14:00", "end_time": "15:50", "spaces_available": "49", "number_registered": "48", "units": "4.0", "dclass_code": "R", "instructorName": ["Hsieh,Yu-Wei"]}, {"type": "Dis", "day": "T", "start_time": "18:00", "end_time": "18:50", "spaces_available": "25", "number_registered": "25", "units": "0.0", "dclass_code": "R", "instructorName": ""}, {"type": "Dis", "day": "F", "start_time": "13:00", "end_time": "13:50", "spaces_available": "24", "number_registered": "23", "units": "0.0", "dclass_code": "R", "instructorName": ""}]