[{"type": "Lec", "day": "F", "start_time": "10:00", "end_time": "11:50", "spaces_available": "15", "number_registered": "15", "units": "2.0", "dclass_code": "R", "instructorName": ["Bottom,James"]}, {"type": "Lec", "day": "W", "start_time": "12:00", "end_time": "13:50", "spaces_available": "15", "number_registered": "11", "units": "2.0", "dclass_code": "D", "instructorName": ["Albertson,David"]}, {"type": "Lec", "day": "M", "start_time": "14:00", "end_time": "15:50", "spaces_available": "15", "number_registered": "15", "units": "2.0", "dclass_code": "R", "instructorName": ["Phillips,Kenneth"]}, {"type": "Lec", "day": "M", "start_time": "14:00", "end_time": "15:50", "spaces_available": "15", "number_registered": "13", "units": "2.0", "dclass_code": "D", "instructorName": ["Meshkati,Najmedin"]}, {"type": "Lec", "day": "T", "start_time": "14:00", "end_time": "15:50", "spaces_available": "15", "number_registered": "14", "units": "2.0", "dclass_code": "R", "instructorName": ["Girandola,Bob"]}, {"type": "Lec", "day": "T", "start_time": "14:00", "end_time": "15:50", "spaces_available": "15", "number_registered": "9", "units": "2.0", "dclass_code": "R", "instructorName": ["Anderson,Anthony"]}, {"type": "Lec", "day": "T", "start_time": "14:00", "end_time": "15:50", "spaces_available": "15", "number_registered": "4", "units": "2.0", "dclass_code": "R", "instructorName": ["Koffman,Henry"]}, {"type": "Lec", "day": "W", "start_time": "14:00", "end_time": "15:50", "spaces_available": "15", "number_registered": "14", "units": "2.0", "dclass_code": "R", "instructorName": ["Biersach,Bill"]}, {"type": "Lec", "day": "W", "start_time": "14:00", "end_time": "15:50", "spaces_available": "15", "number_registered": "7", "units": "2.0", "dclass_code": "D", "instructorName": ["Ullmann,Michaela"]}, {"type": "Lec", "day": "H", "start_time": "14:00", "end_time": "15:50", "spaces_available": "15", "number_registered": "15", "units": "2.0", "dclass_code": "R", "instructorName": ["Fliegel,Richard"]}, {"type": "Lec", "day": "W", "start_time": "15:00", "end_time": "16:50", "spaces_available": "15", "number_registered": "15", "units": "2.0", "dclass_code": "R", "instructorName": ["Burle,Nathalie"]}, {"type": "Lec", "day": "H", "start_time": "16:00", "end_time": "17:50", "spaces_available": "15", "number_registered": "12", "units": "2.0", "dclass_code": "R", "instructorName": ["Harris,Susan"]}]