[{"type": "Lec", "day": "W", "start_time": "18:00", "end_time": "21:20", "spaces_available": "28", "number_registered": "13", "units": "4.0", "dclass_code": "D", "instructorName": ["Greenwald,Howard"]}, {"type": "Lec", "day": "W", "start_time": "14:00", "end_time": "17:20", "spaces_available": "28", "number_registered": "28", "units": "4.0", "dclass_code": "D", "instructorName": ["Dalton,Philip"]}, {"type": "Lec", "day": {}, "start_time": "TBA", "end_time": "TBA", "spaces_available": "28", "number_registered": "18", "units": "4.0", "dclass_code": "D", "instructorName": ["Lewis,Lavonna"]}]