[{"type": "Lec", "day": "MWF", "start_time": "09:00", "end_time": "09:50", "spaces_available": "49", "number_registered": "45", "units": "4.0", "dclass_code": "R", "instructorName": ["Bartroff,Jay"]}, {"type": "Dis", "day": "TH", "start_time": "12:00", "end_time": "12:50", "spaces_available": "25", "number_registered": "21", "units": "0.0", "dclass_code": "R", "instructorName": ""}, {"type": "Dis", "day": "TH", "start_time": "13:00", "end_time": "13:50", "spaces_available": "25", "number_registered": "24", "units": "0.0", "dclass_code": "R", "instructorName": ""}, {"type": "Lec", "day": "MWF", "start_time": "09:00", "end_time": "09:50", "spaces_available": "49", "number_registered": "37", "units": "4.0", "dclass_code": "R", "instructorName": ["Rosen,Gary"]}, {"type": "Dis", "day": "TH", "start_time": "12:00", "end_time": "12:50", "spaces_available": "25", "number_registered": "13", "units": "0.0", "dclass_code": "R", "instructorName": ""}, {"type": "Dis", "day": "TH", "start_time": "13:00", "end_time": "13:50", "spaces_available": "26", "number_registered": "24", "units": "0.0", "dclass_code": "R", "instructorName": ""}]